Cfg_Loader-0.2.2.dist-info/METADATA
Cfg_Loader-0.2.2.dist-info/RECORD
Cfg_Loader-0.2.2.dist-info/WHEEL
Cfg_Loader-0.2.2.dist-info/top_level.txt
cfg_loader/__init__.py
cfg_loader/exceptions.py
cfg_loader/fields.py
cfg_loader/interpolator.py
cfg_loader/loader.py
cfg_loader/utils.py
cfg_loader/schema/__init__.py
cfg_loader/schema/base.py
tests/__init__.py
tests/conftest.py
tests/test_fields.py
tests/test_import.py
tests/test_interpolator.py
tests/test_loader.py
tests/test_schema.py
tests/test_utils.py
