Metadata-Version: 2.1
Name: Cfg-Loader
Version: 0.2.2
Summary: A library that allows to easily load configuration settings.
Home-page: https://github.com/nmvalera/cfg-loader
Author: Nicolas Maurice
Author-email: nicolas.maurice.valera@gmail.com
Maintainer: ConsenSys France
License: Copyright (c) 2017 by ConsenSys France and contributors.
Requires-Dist: marshmallow (==3.0.0b11)
Requires-Dist: PyYAML (>=3.12)
Provides-Extra: dev
Requires-Dist: flake8; extra == 'dev'
Requires-Dist: autoflake; extra == 'dev'
Requires-Dist: autopep8; extra == 'dev'
Requires-Dist: coverage; extra == 'dev'
Requires-Dist: pytest (>=3); extra == 'dev'
Requires-Dist: tox; extra == 'dev'
Requires-Dist: sphinx; extra == 'dev'
Requires-Dist: sphinx-rtd-theme; extra == 'dev'
Provides-Extra: doc
Requires-Dist: sphinx; extra == 'doc'
Requires-Dist: sphinx-rtd-theme; extra == 'doc'
